aimmo_models-0.0.7.data/purelib/aimmo/__init__.py
aimmo_models-0.0.7.data/purelib/aimmo/models.py
aimmo_models-0.0.7.data/purelib/aimmo/models/__init__.py
aimmo_models-0.0.7.data/purelib/aimmo/models/_model.py
aimmo_models-0.0.7.data/purelib/aimmo/models/model.py
aimmo_models-0.0.7.data/purelib/aimmo/models/server.py
aimmo_models-0.0.7.dist-info/LICENSE
aimmo_models-0.0.7.dist-info/METADATA
aimmo_models-0.0.7.dist-info/WHEEL
aimmo_models-0.0.7.dist-info/entry_points.txt
aimmo_models-0.0.7.dist-info/top_level.txt
aimmo_models-0.0.7.dist-info/RECORD
